{
    "unix_timestamp_utc_previous_file": 1553628002,
    "hash_md5_previous_file": "6f3713fec92459a15e93da9cf122b232",
    "transactions": [
        {
            "txid": "15536403-9768-78fd-31c6-3926091b9176",
            "type": "transfer",
            "status": "completed",
            "datetime": 1553640397,
            "sender": "",
            "recipient": "",
            "initiator": "0x787507c15a80c45e287f1da973ca01a6a8ab0c2d",
            "knleader": "",
            "amount": "0x0",
            "fee": "0x0",
            "message": "{\"action\":\"OnAuctionDone\",\"login\":\"893ab383c2959616caf471ae40378a4c5c56e807\",\"petId\":21614}",
            "product": "",
            "result": ""
        },
        {
            "txid": "15536403-9965-6693-30ea-035708c47a1b",
            "type": "transfer",
            "status": "completed",
            "datetime": 1553640399,
            "sender": "0x893ab383c2959616caf471ae40378a4c5c56e807",
            "recipient": "0x787507c15a80c45e287f1da973ca01a6a8ab0c2d",
            "initiator": "0x787507c15a80c45e287f1da973ca01a6a8ab0c2d",
            "knleader": "",
            "amount": "0x0",
            "fee": "0x0",
            "message": "",
            "product": "",
            "result": ""
        },
        {
            "txid": "15536404-2225-34d0-f99d-1a0d099c3f75",
            "type": "transfer",
            "status": "completed",
            "datetime": 1553640422,
            "sender": "",
            "recipient": "",
            "initiator": "0x787507c15a80c45e287f1da973ca01a6a8ab0c2d",
            "knleader": "",
            "amount": "0x0",
            "fee": "0x0",
            "message": "{\"action\":\"OnAuctionDone\",\"login\":\"893ab383c2959616caf471ae40378a4c5c56e807\",\"petId\":21616}",
            "product": "",
            "result": ""
        },
        {
            "txid": "15536404-2412-197c-1992-58570b44f546",
            "type": "transfer",
            "status": "completed",
            "datetime": 1553640424,
            "sender": "0x893ab383c2959616caf471ae40378a4c5c56e807",
            "recipient": "0x787507c15a80c45e287f1da973ca01a6a8ab0c2d",
            "initiator": "0x787507c15a80c45e287f1da973ca01a6a8ab0c2d",
            "knleader": "",
            "amount": "0x0",
            "fee": "0x0",
            "message": "",
            "product": "",
            "result": ""
        },
        {
            "txid": "15536404-3921-2130-f74a-6d150560c4ea",
            "type": "transfer",
            "status": "completed",
            "datetime": 1553640439,
            "sender": "",
            "recipient": "",
            "initiator": "0x787507c15a80c45e287f1da973ca01a6a8ab0c2d",
            "knleader": "",
            "amount": "0x0",
            "fee": "0x0",
            "message": "{\"action\":\"OnAuctionDone\",\"login\":\"893ab383c2959616caf471ae40378a4c5c56e807\",\"petId\":21617}",
            "product": "",
            "result": ""
        },
        {
            "txid": "15536404-4066-949e-a4d8-3a3b091cf3e9",
            "type": "transfer",
            "status": "completed",
            "datetime": 1553640440,
            "sender": "0x893ab383c2959616caf471ae40378a4c5c56e807",
            "recipient": "0x787507c15a80c45e287f1da973ca01a6a8ab0c2d",
            "initiator": "0x787507c15a80c45e287f1da973ca01a6a8ab0c2d",
            "knleader": "",
            "amount": "0x0",
            "fee": "0x0",
            "message": "",
            "product": "",
            "result": ""
        },
        {
            "txid": "15536404-5859-1644-43f9-fea109972605",
            "type": "transfer",
            "status": "completed",
            "datetime": 1553640458,
            "sender": "",
            "recipient": "",
            "initiator": "0x787507c15a80c45e287f1da973ca01a6a8ab0c2d",
            "knleader": "",
            "amount": "0x0",
            "fee": "0x0",
            "message": "{\"action\":\"OnAuctionDone\",\"login\":\"893ab383c2959616caf471ae40378a4c5c56e807\",\"petId\":21618}",
            "product": "",
            "result": ""
        },
        {
            "txid": "15536404-5988-5756-e90f-fd720f171d3d",
            "type": "transfer",
            "status": "completed",
            "datetime": 1553640459,
            "sender": "0x893ab383c2959616caf471ae40378a4c5c56e807",
            "recipient": "0x787507c15a80c45e287f1da973ca01a6a8ab0c2d",
            "initiator": "0x787507c15a80c45e287f1da973ca01a6a8ab0c2d",
            "knleader": "",
            "amount": "0x0",
            "fee": "0x0",
            "message": "",
            "product": "",
            "result": ""
        },
        {
            "txid": "15536404-7897-28d8-89fb-79fd016b0840",
            "type": "transfer",
            "status": "completed",
            "datetime": 1553640478,
            "sender": "",
            "recipient": "",
            "initiator": "0x787507c15a80c45e287f1da973ca01a6a8ab0c2d",
            "knleader": "",
            "amount": "0x0",
            "fee": "0x0",
            "message": "{\"action\":\"OnAuctionDone\",\"login\":\"893ab383c2959616caf471ae40378a4c5c56e807\",\"petId\":21619}",
            "product": "",
            "result": ""
        },
        {
            "txid": "15536404-8093-9459-79cc-74d20a03ff0f",
            "type": "transfer",
            "status": "completed",
            "datetime": 1553640480,
            "sender": "0x893ab383c2959616caf471ae40378a4c5c56e807",
            "recipient": "0x787507c15a80c45e287f1da973ca01a6a8ab0c2d",
            "initiator": "0x787507c15a80c45e287f1da973ca01a6a8ab0c2d",
            "knleader": "",
            "amount": "0x0",
            "fee": "0x0",
            "message": "",
            "product": "",
            "result": ""
        },
        {
            "txid": "15536461-5141-699a-85f6-8375085944b8",
            "type": "transfer",
            "status": "completed",
            "datetime": 1553646151,
            "sender": "",
            "recipient": "",
            "initiator": "0x787507c15a80c45e287f1da973ca01a6a8ab0c2d",
            "knleader": "",
            "amount": "0x0",
            "fee": "0x0",
            "message": "{\"action\":\"OnAuctionDone\",\"login\":\"893ab383c2959616caf471ae40378a4c5c56e807\",\"petId\":21620}",
            "product": "",
            "result": ""
        },
        {
            "txid": "15536461-5294-6412-f4f7-05d80a024e82",
            "type": "transfer",
            "status": "completed",
            "datetime": 1553646152,
            "sender": "0x893ab383c2959616caf471ae40378a4c5c56e807",
            "recipient": "0x787507c15a80c45e287f1da973ca01a6a8ab0c2d",
            "initiator": "0x787507c15a80c45e287f1da973ca01a6a8ab0c2d",
            "knleader": "",
            "amount": "0x0",
            "fee": "0x0",
            "message": "",
            "product": "",
            "result": ""
        },
        {
            "txid": "15536461-7050-45f6-1326-1745094ab1d8",
            "type": "transfer",
            "status": "completed",
            "datetime": 1553646170,
            "sender": "",
            "recipient": "",
            "initiator": "0x787507c15a80c45e287f1da973ca01a6a8ab0c2d",
            "knleader": "",
            "amount": "0x0",
            "fee": "0x0",
            "message": "{\"action\":\"OnAuctionDone\",\"login\":\"893ab383c2959616caf471ae40378a4c5c56e807\",\"petId\":21621}",
            "product": "",
            "result": ""
        },
        {
            "txid": "15536461-7204-8464-f497-ec26050aa380",
            "type": "transfer",
            "status": "completed",
            "datetime": 1553646172,
            "sender": "0x893ab383c2959616caf471ae40378a4c5c56e807",
            "recipient": "0x787507c15a80c45e287f1da973ca01a6a8ab0c2d",
            "initiator": "0x787507c15a80c45e287f1da973ca01a6a8ab0c2d",
            "knleader": "",
            "amount": "0x0",
            "fee": "0x0",
            "message": "",
            "product": "",
            "result": ""
        }
    ],
    "unix_timestamp_utc": 1553671202
}